nexium_google/__init__.py
nexium_google/spreadsheet/__init__.py
nexium_google/spreadsheet/base_row_model.py
nexium_google/spreadsheet/field.py
nexium_google/spreadsheet/field_type.py
nexium_google/spreadsheet/spreadsheet.py
nexium_google/utils/__init__.py
nexium_google/utils/service_account.py
nexium_google/utils/exceptions/__init__.py
nexium_google/utils/exceptions/service_account.py
nexium_google/youtube/__init__.py
nexium_google-0.1.1.dist-info/LICENSE
nexium_google-0.1.1.dist-info/METADATA
nexium_google-0.1.1.dist-info/WHEEL
nexium_google-0.1.1.dist-info/top_level.txt
nexium_google-0.1.1.dist-info/RECORD
