Metadata-Version: 2.1
Name: nexium_google
Version: 0.1.1
Summary: Convenient integration with Google Services
Home-page: https://github.com/nexium-dev/nexium_google
Author: Nexium
Author-email: info@nexium.me
License: MIT
Classifier: Programming Language :: Python :: 3
Classifier: License :: OSI Approved :: MIT License
Classifier: Operating System :: OS Independent
Requires-Python: >=3.11
License-File: LICENSE
Requires-Dist: google-auth==2.36.0
Requires-Dist: gspread==6.1.4
Requires-Dist: gspread_formatting==1.2.0
Requires-Dist: pytz==2024.2
